{".gitignore": [".gitignore"], "LICENSE": ["LICENSE"], "README.md": ["README.md"], "apis": ["apis"], "beautifulsoup": ["beautifulsoup"], "bookworm": ["bookworm"], "classification": ["classification"], "color-analysis": ["color-analysis"], "command-line-git": ["command-line-git"], "command-line": ["command-line"], "first-steps-with-python": ["first-steps-with-python"], "generative-art": ["generative-art"], "github-pages": ["github-pages"], "google-analytics": ["google-analytics"], "greek-text-analysis": ["greek-text-analysis"], "image-similarity": ["image-similarity"], "inpho-topic-explorer": ["inpho-topic-explorer"], "intro-to-d3": ["intro-to-d3"], "intro-to-ggplot": ["intro-to-ggplot"], "intro-to-git": ["intro-to-git"], "intro-to-javascript": ["intro-to-javascript"], "machine-learning": ["machine-learning"], "named-entity-recognition": ["named-entity-recognition"], "networks": ["networks"], "neural-style-transfer": ["neural-style-transfer"], "portable-tropy": ["portable-tropy"], "react": ["react"], "rstudio-dfrtopics": ["rstudio-dfrtopics"], "story-maps": ["story-maps"], "tableau": ["tableau"], "text-recognition-Intro": ["text-recognition-Intro"], "topic-modeling-python": ["topic-modeling-python"], "web-scraping": ["web-scraping"], "word-vectors": ["word-vectors"]}